MANIFEST.in
README.md
setup.cfg
setup.py
src/requirements.txt
src/test-requirements.txt
src/apb/__init__.py
src/apb/cli.py
src/apb/engine.py
src/apb.egg-info/PKG-INFO
src/apb.egg-info/SOURCES.txt
src/apb.egg-info/dependency_links.txt
src/apb.egg-info/entry_points.txt
src/apb.egg-info/requires.txt
src/apb.egg-info/top_level.txt
src/apb/dat/Dockerfile.j2
src/apb/dat/Makefile.j2
src/apb/dat/apb.yml.j2
src/apb/dat/playbooks/playbook.yml.j2
src/apb/dat/roles/bind/tasks/main.yml.j2
src/apb/dat/roles/deprovision/tasks/main.yml.j2
src/apb/dat/roles/provision/tasks/main.yml.j2
src/apb/dat/roles/unbind/tasks/main.yml.j2