Metadata-Version: 1.1
Name: apb
Version: 1.1.15
Summary: Tooling for managing Ansible Playbook Bundle (APB) projects
Home-page: https://github.com/ansibleplaybookbundle/ansible-playbook-bundle
Author: Fusor
Author-email: ansible-service-broker@redhat.com
License: UNKNOWN
Download-URL: https://github.com/ansibleplaybookbundle/ansible-playbook-bundle/archive/apb1.1.15.tar.gz
Keywords: ansible,playbook,bundle
Platform: UNKNOWN
